src/__init__.py
src/daily_update.py
src/display.py
src/main.py
src/match.py
src/result.py
src/team.py
src/util.py
leaguedaily-1.0.1.dist-info/LICENSE
leaguedaily-1.0.1.dist-info/METADATA
leaguedaily-1.0.1.dist-info/WHEEL
leaguedaily-1.0.1.dist-info/entry_points.txt
leaguedaily-1.0.1.dist-info/RECORD
